{
    "init": {
        "answers": [
            {"content": "ポートフォリオを見たい", "nextId": "portfolio"},
            {"content": "ブログを読みたい", "nextId": "blog"},
            {"content": "小川さんについて詳しく知りたい", "nextId": "detail"},
            {"content": "その他", "nextId": "other"}
        ],
        "question": "こんにちは！小川裕太の紹介botへようこそ！何をご覧になりますか？"
    },
    "portfolio": {
        "answers": [
            {"content": "模写コーディングを見たい", "nextId": "https://ogacon.com/work/"},
            {"content": "PHPによるポートフォリオを見たい", "nextId": "https://ogacon.com/codecafe_minisite/codecafe/join/index.php"},
            {"content": "JavaScriptによるポートフォリオを見たい", "nextId": "https://ogacon.com/pyramid/"},
            {"content": "Unityによるポートフォリオを見たい(PCブラウザ版)", "nextId": "https://ogacon.com/MedalPusher/"},
            {"content": "最初の質問に戻る", "nextId": "init"}
        ],
        "question": "ポートフォリオについてですね！どのようなポートフォリオをご覧になりますか？"
    },
    "blog": {
        "answers": [
            {"content": "案件獲得についての記事を読みたい", "nextId": "https://ogacon.com/programing-orders/"},
            {"content": "PHPの学習に関する記事を読みたい", "nextId": "https://ogacon.com/php/"},
            {"content": "最初の質問に戻る", "nextId": "init"}
        ],
        "question": "ブログについてですね！どんな記事を読みたいですか？"
    },
    "detail": {
        "answers": [
            {"content": "twitterのアカウントを見たい", "nextId": "https://twitter.com/oga_tennis114"},
            {"content": "Githubを見たい", "nextId": "https://github.com/Yuta-Ogawa"},
            {"content": "どんな活動をしているか知りたい", "nextId": "https://ogacon.com/about/"},
            {"content": "最初の質問に戻る", "nextId": "init"}
        ],
        "question": "私について興味を持っていただき、ありがとうございます！どんなことを知りたいですか？"
    },
    "other": {
        "answers": [
            {"content": "問い合わせる", "nextId": "https://ogacon.com/contact/"},
            {"content": "最初の質問に戻る", "nextId": "init"}
        ],
        "question": "その他についてですね！コチラからお問い合わせできます。"
    }
    
}